temp_clust/__init__.py
temp_clust/raw.py
temp_clust/data/TempClust_PptDemo-Tracking_Full.csv
temp_clust/data/aoa.csv
temp_clust/data/item_category_mapping.csv
temp_clust/data/non-familiar_words.csv
temp_clust/data/plot_category_structure.csv
temp_clust/data/temp_clust_recalled_order_01-2022.csv
temp_clust/data/temp_clust_recalled_order_02-2022.csv
temp_clust/data/temp_clust_recalled_order_02-2022b.csv
temp_clust/data/temp_clust_recalled_order_02-2022c.csv
temp_clust/data/temp_clust_recalled_order_04-2022.csv
temp_clust/data/temp_clust_recalled_order_four_01-2022.csv
temp_clust/data/temp_clust_recalled_order_four_02-2022.csv
temp_clust/data/temp_clust_recalled_order_four_02-2022b.csv
temp_clust/data/temp_clust_recalled_order_four_02-2022c.csv
temp_clust/data/temp_clust_recalled_order_four_04-2022.csv
temp_clust-0.1.2.data/scripts/process_files.py
temp_clust-0.1.2.dist-info/LICENSE
temp_clust-0.1.2.dist-info/METADATA
temp_clust-0.1.2.dist-info/WHEEL
temp_clust-0.1.2.dist-info/top_level.txt
temp_clust-0.1.2.dist-info/RECORD
