Metadata-Version: 2.1
Name: temp-clust
Version: 0.1.2
Summary: Package for analyzing free recall and parsing data
Author: Tony Dutcher
Author-email: anthonydutcher1@gmail.com
License: GPL-3.0-or-later
Keywords: free recall,list learning,semantic,psychological behavior
Platform: UNKNOWN
Classifier: Programming Language :: Python :: 3
Classifier: License :: OSI Approved :: GNU General Public License v3 or later (GPLv3+)
Classifier: Operating System :: OS Independent
Requires-Python: >=3.7
License-File: LICENSE
Requires-Dist: numpy
Requires-Dist: scipy
Requires-Dist: pandas
Requires-Dist: matplotlib
Requires-Dist: seaborn
Provides-Extra: test
Requires-Dist: pytest ; extra == 'test'
